feste/__init__.py
feste/compute.py
feste/context.py
feste/graph.py
feste/optimization.py
feste/prompt.py
feste/scheduler.py
feste/task.py
feste/backend/__init__.py
feste/backend/cohere.py
feste/backend/openai.py
feste-0.1.0.dist-info/LICENSE
feste-0.1.0.dist-info/METADATA
feste-0.1.0.dist-info/WHEEL
feste-0.1.0.dist-info/top_level.txt
feste-0.1.0.dist-info/RECORD
