Metadata-Version: 2.1
Name: feste
Version: 0.1.0
Summary: Scalable NLP compositions with graph optimizations.
Home-page: https://github.com/perone/feste
Author: Christian S. Perone
Author-email: christian.perone@gmail.com
Project-URL: Bug Tracker, https://github.com/perone/feste/issues
Classifier: Programming Language :: Python :: 3
Classifier: License :: OSI Approved :: MIT License
Classifier: Operating System :: OS Independent
Requires-Python: >=3.8
License-File: LICENSE
Requires-Dist: python-iso639 (>=2023.2.4)
Requires-Dist: jinja2 (>=3.1.2)
Requires-Dist: toolz (>=0.12.0)
Requires-Dist: openai
Requires-Dist: rich (>=13.3.1)
Requires-Dist: dask (>=2023.2.0)
Requires-Dist: cohere (>=3.9.0)
Requires-Dist: cloudpickle (>=2.2.1)
Provides-Extra: dev
Requires-Dist: pytest (>=7.2.1) ; extra == 'dev'
Requires-Dist: mypy (>=1.0.1) ; extra == 'dev'
Requires-Dist: flake8 (>=6.0.0) ; extra == 'dev'
Requires-Dist: pytest-cov (>=4.0.0) ; extra == 'dev'
Requires-Dist: sphinx (>=6.1.3) ; extra == 'dev'
Requires-Dist: pydata-sphinx-theme (>=0.13.0) ; extra == 'dev'
Requires-Dist: sphinx-tabs (>=3.4.1) ; extra == 'dev'
Requires-Dist: nbsphinx (>=0.8.12) ; extra == 'dev'
Requires-Dist: ipykernel (>=6.21.2) ; extra == 'dev'
Requires-Dist: isort (>=5.12.0) ; extra == 'dev'
Requires-Dist: invoke (>=2.0.0) ; extra == 'dev'
Requires-Dist: pydocstyle (>=6.3.0) ; extra == 'dev'
Requires-Dist: twine (>=4.0.2) ; extra == 'dev'
Requires-Dist: sphinx-autobuild (>=2021.3.14) ; extra == 'dev'
Requires-Dist: ipywidgets (>=8.0.4) ; extra == 'dev'
Requires-Dist: sphinxcontrib-bibtex (>=2.5.0) ; extra == 'dev'
